lomapy/__init__.py
lomapy/categorias.py
lomapy/lojas.py
lomapy/ofertas.py
lomapy/recursos/__init__.py
lomapy/recursos/manipulador_requisicoes.py
lomapy/recursos/rotas/__init__.py
lomapy/recursos/rotas/rotas_categoria.py
lomapy/recursos/rotas/rotas_loja.py
lomapy/recursos/rotas/rotas_oferta.py
lomapy/recursos/sdk/__init__.py
lomapy/recursos/sdk/sdk.py
tests/__init__.py
tests/categorias_test.py
tests/lojas_test.py
tests/ofertas_test.py
tests/recursos/__init__.py
lomapy-0.3.5.dist-info/LICENSE
lomapy-0.3.5.dist-info/METADATA
lomapy-0.3.5.dist-info/WHEEL
lomapy-0.3.5.dist-info/top_level.txt
lomapy-0.3.5.dist-info/RECORD
