Metadata-Version: 2.1
Name: lomapy
Version: 0.3.5
Summary: Lomapy
Home-page: https://github.com/AlanTaranti/Lomapy
Author: Alan Taranti
Author-email: alan.taranti@gmail.com
License: MIT
Keywords: lomapy,lomadee
Platform: UNKNOWN
Classifier: Intended Audience :: Developers
Classifier: Intended Audience :: System Administrators
Classifier: Operating System :: OS Independent
Classifier: Topic :: Software Development
Classifier: Environment :: Web Environment
Classifier: Programming Language :: Python :: 3.5
Classifier: Programming Language :: Python :: 3.6
Classifier: Programming Language :: Python :: 3.7
Classifier: License :: OSI Approved :: MIT License
Requires-Dist: requests
Provides-Extra: testing
Requires-Dist: pytest ; extra == 'testing'
Requires-Dist: pytest-cov ; extra == 'testing'
Requires-Dist: python-dotenv ; extra == 'testing'
